remote_script_tool/__init__.py
remote_script_tool-1.0.2.dist-info/METADATA
remote_script_tool-1.0.2.dist-info/WHEEL
remote_script_tool-1.0.2.dist-info/licenses/LICENSE
remote_script_tool-1.0.2.dist-info/RECORD
